sd_regex_testing/__init__.py
sd_regex_testing/interactive.py
sd_regex_testing/regex_testing.py
sd_regex_testing-1.0.2.dist-info/LICENSE
sd_regex_testing-1.0.2.dist-info/METADATA
sd_regex_testing-1.0.2.dist-info/WHEEL
sd_regex_testing-1.0.2.dist-info/entry_points.txt
sd_regex_testing-1.0.2.dist-info/RECORD
