Metadata-Version: 2.1
Name: sd-regex-testing
Version: 1.0.2
Summary: A set of tools for testing SmokeDetector regexes
Home-page: https://github.com/Andrew5057/sd-regex-testing
License: GPL-3.0-or-later
Author: anerdw
Author-email: yimandrew27@gmail.com
Requires-Python: >=3.11,<4.0
Classifier: License :: OSI Approved :: GNU General Public License v3 or later (GPLv3+)
Classifier: Programming Language :: Python :: 3
Classifier: Programming Language :: Python :: 3.11
Classifier: Programming Language :: Python :: 3.12
Requires-Dist: polars (>=1.6.0,<2.0.0)
Project-URL: Repository, https://github.com/Andrew5057/sd-regex-testing
